{
  "version": "1.1",
  "player": {
    "name": "Aventurier",
    "level": 5,
    "xp": 25,
    "xp_to_next_level": 672,
    "base_stats": {
      "armure": 0.0,
      "atk": 16.200000000000003,
      "blocage": 0.0,
      "bouclier": 0.0,
      "chance_double_drop_pct": 0.0,
      "cooldown_reduc": 0.0,
      "cout_reroll_pct": 0.0,
      "crit_chance": 7.0,
      "crit_degats": 300.0,
      "def_stat": 1.2,
      "degats_feu": 0.0,
      "degats_foudre": 0.0,
      "degats_glace": 0.0,
      "degats_lumiere": 0.0,
      "degats_ombre": 0.0,
      "degats_physique": 0.0,
      "degats_poison": 0.0,
      "epines": 0.0,
      "esquive": 0.0,
      "flag_boss_slayer": 0.0,
      "flag_execute": 0.0,
      "flag_reroll_free_chance": 0.0,
      "flag_resource_spirit": 0.0,
      "gain_or_pct": 0.0,
      "gain_xp_pct": 0.0,
      "gather_power_herb": 0.0,
      "gather_power_ore": 0.0,
      "gather_power_wood": 0.0,
      "hp_current": 1572065715.2649958,
      "hp_max": 146.0,
      "hp_regen": 0.39999999999999997,
      "precision": 0.0,
      "proc_double_coup_chance": 0.0,
      "proc_etourdissement_chance": 0.0,
      "proc_poison_chance": 0.0,
      "proc_saignement_chance": 0.0,
      "rendement_demantelement_pct": 0.0,
      "resistance_elementaire": 0.0,
      "ressources_gagnees_pct": 0.0,
      "vitesse_attaque": 1.8,
      "vitesse_craft_pct": 0.0,
      "vitesse_recolte_pct": 0.0,
      "vol_vie": 0.0
    },
    "equipment": {
      "weapon": null,
      "helmet": null,
      "chest": null,
      "legs": null,
      "boots": null,
      "gloves": null,
      "ring1": null,
      "ring2": null,
      "amulet": null,
      "tool_ore": {
        "id": "2e44f6a6-c5d2-41b4-aae0-ea05b6c30486",
        "base_id": "tool__pioche__t1",
        "name": "Pioche T1",
        "slot": "tool_ore",
        "tier": "t1",
        "rarity_id": "rare",
        "quality_id": "poor",
        "base_stats": {
          "armure": 0.0,
          "atk": 10.0,
          "blocage": 0.0,
          "bouclier": 0.0,
          "chance_double_drop_pct": 0.0,
          "cooldown_reduc": 0.0,
          "cout_reroll_pct": 0.0,
          "crit_chance": 5.0,
          "crit_degats": 150.0,
          "def_stat": 0.0,
          "degats_feu": 0.0,
          "degats_foudre": 0.0,
          "degats_glace": 0.0,
          "degats_lumiere": 0.0,
          "degats_ombre": 0.0,
          "degats_physique": 0.0,
          "degats_poison": 0.0,
          "epines": 0.0,
          "esquive": 0.0,
          "flag_boss_slayer": 0.0,
          "flag_execute": 0.0,
          "flag_reroll_free_chance": 0.0,
          "flag_resource_spirit": 0.0,
          "gain_or_pct": 0.0,
          "gain_xp_pct": 0.0,
          "gather_power_herb": 0.0,
          "gather_power_ore": 5.845394927583327,
          "gather_power_wood": 0.0,
          "hp_current": 100.0,
          "hp_max": 100.0,
          "hp_regen": 0.0,
          "precision": 0.0,
          "proc_double_coup_chance": 0.0,
          "proc_etourdissement_chance": 0.0,
          "proc_poison_chance": 0.0,
          "proc_saignement_chance": 0.0,
          "rendement_demantelement_pct": 0.0,
          "resistance_elementaire": 0.0,
          "ressources_gagnees_pct": 0.0,
          "vitesse_attaque": 1.0,
          "vitesse_craft_pct": 0.0,
          "vitesse_recolte_pct": 0.0,
          "vol_vie": 0.0
        },
        "affixes": [],
        "set_id": null,
        "gold_value": 10,
        "level_requirement": 1,
        "power_score": 130.0,
        "is_equipped": true
      },
      "tool_wood": null,
      "tool_herb": null,
      "outil_hache": {
        "id": "b56fe840-abed-4604-b831-f476f25f3fee",
        "base_id": "outil_hache__cuir__t1",
        "name": "Hache en cuir",
        "slot": "outil_hache",
        "tier": "t1",
        "rarity_id": "common",
        "quality_id": "normal",
        "base_stats": {
          "armure": 0.0,
          "atk": 10.0,
          "blocage": 0.0,
          "bouclier": 0.0,
          "chance_double_drop_pct": 0.684453045572437,
          "cooldown_reduc": 0.0,
          "cout_reroll_pct": 0.0,
          "crit_chance": 5.0,
          "crit_degats": 150.0,
          "def_stat": 0.0,
          "degats_feu": 0.0,
          "degats_foudre": 0.0,
          "degats_glace": 0.0,
          "degats_lumiere": 0.0,
          "degats_ombre": 0.0,
          "degats_physique": 0.0,
          "degats_poison": 0.0,
          "epines": 0.0,
          "esquive": 0.0,
          "flag_boss_slayer": 0.0,
          "flag_execute": 0.0,
          "flag_reroll_free_chance": 0.0,
          "flag_resource_spirit": 0.0,
          "gain_or_pct": 0.0,
          "gain_xp_pct": 0.0,
          "gather_power_herb": 0.0,
          "gather_power_ore": 0.0,
          "gather_power_wood": 3.7417554130424797,
          "hp_current": 100.0,
          "hp_max": 100.0,
          "hp_regen": 0.0,
          "precision": 0.0,
          "proc_double_coup_chance": 0.0,
          "proc_etourdissement_chance": 0.0,
          "proc_poison_chance": 0.0,
          "proc_saignement_chance": 0.0,
          "rendement_demantelement_pct": 0.0,
          "resistance_elementaire": 0.0,
          "ressources_gagnees_pct": 0.0,
          "vitesse_attaque": 1.0,
          "vitesse_craft_pct": 0.0,
          "vitesse_recolte_pct": 0.0,
          "vol_vie": 0.0
        },
        "affixes": [],
        "set_id": null,
        "gold_value": 10,
        "level_requirement": 1,
        "power_score": 130.0,
        "is_equipped": true
      },
      "amulette": {
        "id": "b8027ee5-24de-4316-9c9a-ecdbe7fb6855",
        "base_id": "amulette__cuir__t1",
        "name": "Amulette cuir",
        "slot": "amulette",
        "tier": "t1",
        "rarity_id": "common",
        "quality_id": "normal",
        "base_stats": {
          "armure": 0.0,
          "atk": 10.0,
          "blocage": 0.0,
          "bouclier": 0.0,
          "chance_double_drop_pct": 0.0,
          "cooldown_reduc": 0.059497938959815255,
          "cout_reroll_pct": 0.0,
          "crit_chance": 5.0,
          "crit_degats": 150.0,
          "def_stat": 0.0,
          "degats_feu": 0.0,
          "degats_foudre": 0.0,
          "degats_glace": 0.0,
          "degats_lumiere": 0.0,
          "degats_ombre": 0.0,
          "degats_physique": 0.0,
          "degats_poison": 0.0,
          "epines": 0.0,
          "esquive": 0.0,
          "flag_boss_slayer": 0.0,
          "flag_execute": 0.0,
          "flag_reroll_free_chance": 0.0,
          "flag_resource_spirit": 0.0,
          "gain_or_pct": 0.0,
          "gain_xp_pct": 0.0,
          "gather_power_herb": 0.0,
          "gather_power_ore": 0.0,
          "gather_power_wood": 0.0,
          "hp_current": 100.0,
          "hp_max": 105.7117386024911,
          "hp_regen": 0.0,
          "precision": 0.0,
          "proc_double_coup_chance": 0.0,
          "proc_etourdissement_chance": 0.0,
          "proc_poison_chance": 0.0,
          "proc_saignement_chance": 0.0,
          "rendement_demantelement_pct": 0.0,
          "resistance_elementaire": 0.0,
          "ressources_gagnees_pct": 0.0,
          "vitesse_attaque": 1.0,
          "vitesse_craft_pct": 0.0,
          "vitesse_recolte_pct": 0.0,
          "vol_vie": 0.0
        },
        "affixes": [],
        "set_id": null,
        "gold_value": 10,
        "level_requirement": 1,
        "power_score": 130.5711738602491,
        "is_equipped": true
      },
      "plastron": {
        "id": "8e9882ba-710d-4fac-83c8-6d95ae493c12",
        "base_id": "plastron__tissu__t1",
        "name": "Plastron en tissu",
        "slot": "plastron",
        "tier": "t1",
        "rarity_id": "common",
        "quality_id": "normal",
        "base_stats": {
          "armure": 0.0,
          "atk": 10.0,
          "blocage": 0.0,
          "bouclier": 0.0,
          "chance_double_drop_pct": 0.0,
          "cooldown_reduc": 0.0,
          "cout_reroll_pct": 0.0,
          "crit_chance": 5.0,
          "crit_degats": 150.0,
          "def_stat": 2.2129436005823413,
          "degats_feu": 0.0,
          "degats_foudre": 0.0,
          "degats_glace": 0.0,
          "degats_lumiere": 0.0,
          "degats_ombre": 0.0,
          "degats_physique": 0.0,
          "degats_poison": 0.0,
          "epines": 0.0,
          "esquive": 0.0,
          "flag_boss_slayer": 0.0,
          "flag_execute": 0.0,
          "flag_reroll_free_chance": 0.0,
          "flag_resource_spirit": 0.0,
          "gain_or_pct": 0.0,
          "gain_xp_pct": 0.0,
          "gather_power_herb": 0.0,
          "gather_power_ore": 0.0,
          "gather_power_wood": 0.0,
          "hp_current": 100.0,
          "hp_max": 109.92393750584482,
          "hp_regen": 0.0,
          "precision": 0.0,
          "proc_double_coup_chance": 0.0,
          "proc_etourdissement_chance": 0.0,
          "proc_poison_chance": 0.0,
          "proc_saignement_chance": 0.0,
          "rendement_demantelement_pct": 0.0,
          "resistance_elementaire": 0.0,
          "ressources_gagnees_pct": 0.0,
          "vitesse_attaque": 1.0,
          "vitesse_craft_pct": 0.0,
          "vitesse_recolte_pct": 0.0,
          "vol_vie": 0.0
        },
        "affixes": [],
        "set_id": null,
        "gold_value": 10,
        "level_requirement": 1,
        "power_score": 134.311809151458,
        "is_equipped": true
      },
      "anneau": {
        "id": "4ff2da71-cfb4-4591-8057-4216104abf42",
        "base_id": "anneau__cuir__t1",
        "name": "Anneau cuir",
        "slot": "anneau",
        "tier": "t1",
        "rarity_id": "common",
        "quality_id": "normal",
        "base_stats": {
          "armure": 0.0,
          "atk": 11.06738555007946,
          "blocage": 0.0,
          "bouclier": 0.0,
          "chance_double_drop_pct": 0.0,
          "cooldown_reduc": 0.0,
          "cout_reroll_pct": 0.0,
          "crit_chance": 5.845675290518843,
          "crit_degats": 150.0,
          "def_stat": 0.0,
          "degats_feu": 0.0,
          "degats_foudre": 0.0,
          "degats_glace": 0.0,
          "degats_lumiere": 0.0,
          "degats_ombre": 0.0,
          "degats_physique": 0.0,
          "degats_poison": 0.0,
          "epines": 0.0,
          "esquive": 0.0,
          "flag_boss_slayer": 0.0,
          "flag_execute": 0.0,
          "flag_reroll_free_chance": 0.0,
          "flag_resource_spirit": 0.0,
          "gain_or_pct": 0.0,
          "gain_xp_pct": 0.0,
          "gather_power_herb": 0.0,
          "gather_power_ore": 0.0,
          "gather_power_wood": 0.0,
          "hp_current": 100.0,
          "hp_max": 100.0,
          "hp_regen": 0.0,
          "precision": 0.0,
          "proc_double_coup_chance": 0.0,
          "proc_etourdissement_chance": 0.0,
          "proc_poison_chance": 0.0,
          "proc_saignement_chance": 0.0,
          "rendement_demantelement_pct": 0.0,
          "resistance_elementaire": 0.0,
          "ressources_gagnees_pct": 0.0,
          "vitesse_attaque": 1.0,
          "vitesse_craft_pct": 0.0,
          "vitesse_recolte_pct": 0.0,
          "vol_vie": 0.0
        },
        "affixes": [],
        "set_id": null,
        "gold_value": 10,
        "level_requirement": 1,
        "power_score": 134.67179697171545,
        "is_equipped": true
      },
      "bouclier": {
        "id": "99d70f59-ca0e-4e72-ab41-1bffb5a52d68",
        "base_id": "bouclier__cuir__t1",
        "name": "Bouclier en cuir",
        "slot": "bouclier",
        "tier": "t1",
        "rarity_id": "uncommon",
        "quality_id": "normal",
        "base_stats": {
          "armure": 0.0,
          "atk": 10.0,
          "blocage": 1.1575155681850484,
          "bouclier": 0.0,
          "chance_double_drop_pct": 0.0,
          "cooldown_reduc": 0.0,
          "cout_reroll_pct": 0.0,
          "crit_chance": 5.0,
          "crit_degats": 150.0,
          "def_stat": 2.2540861005301953,
          "degats_feu": 0.0,
          "degats_foudre": 0.0,
          "degats_glace": 0.0,
          "degats_lumiere": 0.0,
          "degats_ombre": 0.0,
          "degats_physique": 0.0,
          "degats_poison": 0.0,
          "epines": 0.0,
          "esquive": 0.0,
          "flag_boss_slayer": 0.0,
          "flag_execute": 0.0,
          "flag_reroll_free_chance": 0.0,
          "flag_resource_spirit": 0.0,
          "gain_or_pct": 0.0,
          "gain_xp_pct": 0.0,
          "gather_power_herb": 0.0,
          "gather_power_ore": 0.0,
          "gather_power_wood": 0.0,
          "hp_current": 100.0,
          "hp_max": 100.0,
          "hp_regen": 0.0,
          "precision": 0.0,
          "proc_double_coup_chance": 0.0,
          "proc_etourdissement_chance": 0.0,
          "proc_poison_chance": 0.0,
          "proc_saignement_chance": 0.0,
          "rendement_demantelement_pct": 0.0,
          "resistance_elementaire": 0.0,
          "ressources_gagnees_pct": 0.0,
          "vitesse_attaque": 1.0,
          "vitesse_craft_pct": 0.0,
          "vitesse_recolte_pct": 0.0,
          "vol_vie": 0.0
        },
        "affixes": [],
        "set_id": null,
        "gold_value": 10,
        "level_requirement": 1,
        "power_score": 133.3811291507953,
        "is_equipped": true
      },
      "outil_serpe": {
        "id": "9f23ad7b-14de-4147-8934-5c4cf1cd6670",
        "base_id": "outil_serpe__cuir__t1",
        "name": "Serpe en cuir",
        "slot": "outil_serpe",
        "tier": "t1",
        "rarity_id": "common",
        "quality_id": "normal",
        "base_stats": {
          "armure": 0.0,
          "atk": 10.0,
          "blocage": 0.0,
          "bouclier": 0.0,
          "chance_double_drop_pct": 0.8795809244553794,
          "cooldown_reduc": 0.0,
          "cout_reroll_pct": 0.0,
          "crit_chance": 5.0,
          "crit_degats": 150.0,
          "def_stat": 0.0,
          "degats_feu": 0.0,
          "degats_foudre": 0.0,
          "degats_glace": 0.0,
          "degats_lumiere": 0.0,
          "degats_ombre": 0.0,
          "degats_physique": 0.0,
          "degats_poison": 0.0,
          "epines": 0.0,
          "esquive": 0.0,
          "flag_boss_slayer": 0.0,
          "flag_execute": 0.0,
          "flag_reroll_free_chance": 0.0,
          "flag_resource_spirit": 0.0,
          "gain_or_pct": 0.0,
          "gain_xp_pct": 0.0,
          "gather_power_herb": 4.369029293563811,
          "gather_power_ore": 0.0,
          "gather_power_wood": 0.0,
          "hp_current": 100.0,
          "hp_max": 100.0,
          "hp_regen": 0.0,
          "precision": 0.0,
          "proc_double_coup_chance": 0.0,
          "proc_etourdissement_chance": 0.0,
          "proc_poison_chance": 0.0,
          "proc_saignement_chance": 0.0,
          "rendement_demantelement_pct": 0.0,
          "resistance_elementaire": 0.0,
          "ressources_gagnees_pct": 0.0,
          "vitesse_attaque": 1.0,
          "vitesse_craft_pct": 0.0,
          "vitesse_recolte_pct": 0.0,
          "vol_vie": 0.0
        },
        "affixes": [],
        "set_id": null,
        "gold_value": 10,
        "level_requirement": 1,
        "power_score": 130.0,
        "is_equipped": true
      },
      "outil_pioche": {
        "id": "cd8b63f8-8c0b-4e5e-9117-769c9b694c63",
        "base_id": "outil_pioche__cuir__t1",
        "name": "Pioche en cuir",
        "slot": "outil_pioche",
        "tier": "t1",
        "rarity_id": "uncommon",
        "quality_id": "poor",
        "base_stats": {
          "armure": 0.0,
          "atk": 10.0,
          "blocage": 0.0,
          "bouclier": 0.0,
          "chance_double_drop_pct": 0.1414901903301834,
          "cooldown_reduc": 0.0,
          "cout_reroll_pct": 0.0,
          "crit_chance": 5.0,
          "crit_degats": 150.0,
          "def_stat": 0.0,
          "degats_feu": 0.0,
          "degats_foudre": 0.0,
          "degats_glace": 0.0,
          "degats_lumiere": 0.0,
          "degats_ombre": 0.0,
          "degats_physique": 0.0,
          "degats_poison": 0.0,
          "epines": 0.0,
          "esquive": 0.0,
          "flag_boss_slayer": 0.0,
          "flag_execute": 0.0,
          "flag_reroll_free_chance": 0.0,
          "flag_resource_spirit": 0.0,
          "gain_or_pct": 0.0,
          "gain_xp_pct": 0.0,
          "gather_power_herb": 0.0,
          "gather_power_ore": 3.492267017795128,
          "gather_power_wood": 0.0,
          "hp_current": 100.0,
          "hp_max": 100.0,
          "hp_regen": 0.0,
          "precision": 0.0,
          "proc_double_coup_chance": 0.0,
          "proc_etourdissement_chance": 0.0,
          "proc_poison_chance": 0.0,
          "proc_saignement_chance": 0.0,
          "rendement_demantelement_pct": 0.0,
          "resistance_elementaire": 0.0,
          "ressources_gagnees_pct": 0.0,
          "vitesse_attaque": 1.0,
          "vitesse_craft_pct": 0.0,
          "vitesse_recolte_pct": 0.0,
          "vol_vie": 0.0
        },
        "affixes": [],
        "set_id": null,
        "gold_value": 10,
        "level_requirement": 1,
        "power_score": 130.0,
        "is_equipped": true
      },
      "casque": {
        "id": "710b5fac-248b-4d9b-b898-8bdcc3665ca0",
        "base_id": "casque__cuir__t1",
        "name": "Casque en cuir",
        "slot": "casque",
        "tier": "t1",
        "rarity_id": "uncommon",
        "quality_id": "poor",
        "base_stats": {
          "armure": 0.0,
          "atk": 10.0,
          "blocage": 0.0,
          "bouclier": 0.0,
          "chance_double_drop_pct": 0.0,
          "cooldown_reduc": 0.0,
          "cout_reroll_pct": 0.0,
          "crit_chance": 5.0,
          "crit_degats": 150.0,
          "def_stat": 1.654989972695117,
          "degats_feu": 0.0,
          "degats_foudre": 0.0,
          "degats_glace": 0.0,
          "degats_lumiere": 0.0,
          "degats_ombre": 0.0,
          "degats_physique": 0.0,
          "degats_poison": 0.0,
          "epines": 0.0,
          "esquive": 0.0,
          "flag_boss_slayer": 0.0,
          "flag_execute": 0.0,
          "flag_reroll_free_chance": 0.0,
          "flag_resource_spirit": 0.0,
          "gain_or_pct": 0.0,
          "gain_xp_pct": 0.0,
          "gather_power_herb": 0.0,
          "gather_power_ore": 0.0,
          "gather_power_wood": 0.0,
          "hp_current": 100.0,
          "hp_max": 103.95489132819033,
          "hp_regen": 0.0,
          "precision": 0.0,
          "proc_double_coup_chance": 0.0,
          "proc_etourdissement_chance": 0.0,
          "proc_poison_chance": 0.0,
          "proc_saignement_chance": 0.0,
          "rendement_demantelement_pct": 0.0,
          "resistance_elementaire": 0.0,
          "ressources_gagnees_pct": 0.0,
          "vitesse_attaque": 1.0,
          "vitesse_craft_pct": 0.0,
          "vitesse_recolte_pct": 0.0,
          "vol_vie": 0.0
        },
        "affixes": [],
        "set_id": null,
        "gold_value": 10,
        "level_requirement": 1,
        "power_score": 132.87797409186172,
        "is_equipped": true
      },
      "gants": {
        "id": "eda48ee8-74ed-4eb0-a3ce-4d7493624988",
        "base_id": "gants__cuir__t1",
        "name": "Gants en cuir",
        "slot": "gants",
        "tier": "t1",
        "rarity_id": "common",
        "quality_id": "poor",
        "base_stats": {
          "armure": 0.0,
          "atk": 10.0,
          "blocage": 0.0,
          "bouclier": 0.0,
          "chance_double_drop_pct": 0.0,
          "cooldown_reduc": 0.0,
          "cout_reroll_pct": 0.0,
          "crit_chance": 5.0,
          "crit_degats": 150.0,
          "def_stat": 0.7916299051211981,
          "degats_feu": 0.0,
          "degats_foudre": 0.0,
          "degats_glace": 0.0,
          "degats_lumiere": 0.0,
          "degats_ombre": 0.0,
          "degats_physique": 0.0,
          "degats_poison": 0.0,
          "epines": 0.0,
          "esquive": 0.0,
          "flag_boss_slayer": 0.0,
          "flag_execute": 0.0,
          "flag_reroll_free_chance": 0.0,
          "flag_resource_spirit": 0.0,
          "gain_or_pct": 0.0,
          "gain_xp_pct": 0.0,
          "gather_power_herb": 0.0,
          "gather_power_ore": 0.0,
          "gather_power_wood": 0.0,
          "hp_current": 100.0,
          "hp_max": 100.0,
          "hp_regen": 0.0,
          "precision": 0.0,
          "proc_double_coup_chance": 0.0,
          "proc_etourdissement_chance": 0.0,
          "proc_poison_chance": 0.0,
          "proc_saignement_chance": 0.0,
          "rendement_demantelement_pct": 0.0,
          "resistance_elementaire": 0.0,
          "ressources_gagnees_pct": 0.0,
          "vitesse_attaque": 1.0898950975745358,
          "vitesse_craft_pct": 0.0,
          "vitesse_recolte_pct": 0.0,
          "vol_vie": 0.0
        },
        "affixes": [],
        "set_id": null,
        "gold_value": 10,
        "level_requirement": 1,
        "power_score": 131.18744485768178,
        "is_equipped": true
      },
      "arme": {
        "id": "b5653b7b-57d0-42a4-8b51-77049d6ebae8",
        "base_id": "arme__cuir__t1",
        "name": "Bâton en cuir",
        "slot": "arme",
        "tier": "t1",
        "rarity_id": "common",
        "quality_id": "poor",
        "base_stats": {
          "armure": 0.0,
          "atk": 14.083462048900524,
          "blocage": 0.0,
          "bouclier": 0.0,
          "chance_double_drop_pct": 0.0,
          "cooldown_reduc": 0.0,
          "cout_reroll_pct": 0.0,
          "crit_chance": 5.277729924252645,
          "crit_degats": 150.0,
          "def_stat": 0.0,
          "degats_feu": 0.0,
          "degats_foudre": 0.0,
          "degats_glace": 0.0,
          "degats_lumiere": 0.0,
          "degats_ombre": 0.0,
          "degats_physique": 0.0,
          "degats_poison": 0.0,
          "epines": 0.0,
          "esquive": 0.0,
          "flag_boss_slayer": 0.0,
          "flag_execute": 0.0,
          "flag_reroll_free_chance": 0.0,
          "flag_resource_spirit": 0.0,
          "gain_or_pct": 0.0,
          "gain_xp_pct": 0.0,
          "gather_power_herb": 0.0,
          "gather_power_ore": 0.0,
          "gather_power_wood": 0.0,
          "hp_current": 100.0,
          "hp_max": 100.0,
          "hp_regen": 0.0,
          "precision": 0.0,
          "proc_double_coup_chance": 0.0,
          "proc_etourdissement_chance": 0.0,
          "proc_poison_chance": 0.0,
          "proc_saignement_chance": 0.0,
          "rendement_demantelement_pct": 0.0,
          "resistance_elementaire": 0.0,
          "ressources_gagnees_pct": 0.0,
          "vitesse_attaque": 1.0,
          "vitesse_craft_pct": 0.0,
          "vitesse_recolte_pct": 0.0,
          "vol_vie": 0.0
        },
        "affixes": [],
        "set_id": null,
        "gold_value": 10,
        "level_requirement": 1,
        "power_score": 139.00011387055898,
        "is_equipped": true
      }
    },
    "inventory": [
      {
        "id": "a0008da3-a89a-46b0-a271-232787a6365c",
        "base_id": "tool__pioche__t1",
        "name": "Pioche T1",
        "slot": "tool_ore",
        "tier": "t1",
        "rarity_id": "common",
        "quality_id": "poor",
        "base_stats": {
          "armure": 0.0,
          "atk": 10.0,
          "blocage": 0.0,
          "bouclier": 0.0,
          "chance_double_drop_pct": 0.0,
          "cooldown_reduc": 0.0,
          "cout_reroll_pct": 0.0,
          "crit_chance": 5.0,
          "crit_degats": 150.0,
          "def_stat": 0.0,
          "degats_feu": 0.0,
          "degats_foudre": 0.0,
          "degats_glace": 0.0,
          "degats_lumiere": 0.0,
          "degats_ombre": 0.0,
          "degats_physique": 0.0,
          "degats_poison": 0.0,
          "epines": 0.0,
          "esquive": 0.0,
          "flag_boss_slayer": 0.0,
          "flag_execute": 0.0,
          "flag_reroll_free_chance": 0.0,
          "flag_resource_spirit": 0.0,
          "gain_or_pct": 0.0,
          "gain_xp_pct": 0.0,
          "gather_power_herb": 0.0,
          "gather_power_ore": 5.726490709926537,
          "gather_power_wood": 0.0,
          "hp_current": 100.0,
          "hp_max": 100.0,
          "hp_regen": 0.0,
          "precision": 0.0,
          "proc_double_coup_chance": 0.0,
          "proc_etourdissement_chance": 0.0,
          "proc_poison_chance": 0.0,
          "proc_saignement_chance": 0.0,
          "rendement_demantelement_pct": 0.0,
          "resistance_elementaire": 0.0,
          "ressources_gagnees_pct": 0.0,
          "vitesse_attaque": 1.0,
          "vitesse_craft_pct": 0.0,
          "vitesse_recolte_pct": 0.0,
          "vol_vie": 0.0
        },
        "affixes": [],
        "set_id": null,
        "gold_value": 10,
        "level_requirement": 1,
        "power_score": 130.0,
        "is_equipped": false
      },
      {
        "id": "67beb12f-fb39-4fc7-855a-3b93c973b114",
        "base_id": "arme__tissu__t1",
        "name": "Épée en tissu",
        "slot": "arme",
        "tier": "t1",
        "rarity_id": "common",
        "quality_id": "poor",
        "base_stats": {
          "armure": 0.0,
          "atk": 13.761778454668915,
          "blocage": 0.0,
          "bouclier": 0.0,
          "chance_double_drop_pct": 0.0,
          "cooldown_reduc": 0.0,
          "cout_reroll_pct": 0.0,
          "crit_chance": 5.114903527506247,
          "crit_degats": 150.0,
          "def_stat": 0.0,
          "degats_feu": 0.0,
          "degats_foudre": 0.0,
          "degats_glace": 0.0,
          "degats_lumiere": 0.0,
          "degats_ombre": 0.0,
          "degats_physique": 0.0,
          "degats_poison": 0.0,
          "epines": 0.0,
          "esquive": 0.0,
          "flag_boss_slayer": 0.0,
          "flag_execute": 0.0,
          "flag_reroll_free_chance": 0.0,
          "flag_resource_spirit": 0.0,
          "gain_or_pct": 0.0,
          "gain_xp_pct": 0.0,
          "gather_power_herb": 0.0,
          "gather_power_ore": 0.0,
          "gather_power_wood": 0.0,
          "hp_current": 100.0,
          "hp_max": 100.0,
          "hp_regen": 0.0,
          "precision": 0.0,
          "proc_double_coup_chance": 0.0,
          "proc_etourdissement_chance": 0.0,
          "proc_poison_chance": 0.0,
          "proc_saignement_chance": 0.0,
          "rendement_demantelement_pct": 0.0,
          "resistance_elementaire": 0.0,
          "ressources_gagnees_pct": 0.0,
          "vitesse_attaque": 1.0,
          "vitesse_craft_pct": 0.0,
          "vitesse_recolte_pct": 0.0,
          "vol_vie": 0.0
        },
        "affixes": [],
        "set_id": null,
        "gold_value": 10,
        "level_requirement": 1,
        "power_score": 137.86826749185656,
        "is_equipped": false
      },
      {
        "id": "01b97cbe-af8c-4040-b667-b1323d2715b8",
        "base_id": "gants__cuir__t1",
        "name": "Gants en cuir",
        "slot": "gants",
        "tier": "t1",
        "rarity_id": "common",
        "quality_id": "normal",
        "base_stats": {
          "armure": 0.0,
          "atk": 10.0,
          "blocage": 0.0,
          "bouclier": 0.0,
          "chance_double_drop_pct": 0.0,
          "cooldown_reduc": 0.0,
          "cout_reroll_pct": 0.0,
          "crit_chance": 5.0,
          "crit_degats": 150.0,
          "def_stat": 0.8461332568538902,
          "degats_feu": 0.0,
          "degats_foudre": 0.0,
          "degats_glace": 0.0,
          "degats_lumiere": 0.0,
          "degats_ombre": 0.0,
          "degats_physique": 0.0,
          "degats_poison": 0.0,
          "epines": 0.0,
          "esquive": 0.0,
          "flag_boss_slayer": 0.0,
          "flag_execute": 0.0,
          "flag_reroll_free_chance": 0.0,
          "flag_resource_spirit": 0.0,
          "gain_or_pct": 0.0,
          "gain_xp_pct": 0.0,
          "gather_power_herb": 0.0,
          "gather_power_ore": 0.0,
          "gather_power_wood": 0.0,
          "hp_current": 100.0,
          "hp_max": 100.0,
          "hp_regen": 0.0,
          "precision": 0.0,
          "proc_double_coup_chance": 0.0,
          "proc_etourdissement_chance": 0.0,
          "proc_poison_chance": 0.0,
          "proc_saignement_chance": 0.0,
          "rendement_demantelement_pct": 0.0,
          "resistance_elementaire": 0.0,
          "ressources_gagnees_pct": 0.0,
          "vitesse_attaque": 1.2055035526730544,
          "vitesse_craft_pct": 0.0,
          "vitesse_recolte_pct": 0.0,
          "vol_vie": 0.0
        },
        "affixes": [],
        "set_id": null,
        "gold_value": 10,
        "level_requirement": 1,
        "power_score": 131.26919988528084,
        "is_equipped": false
      },
      {
        "id": "b70eb986-0f45-414e-8db5-7a21f74ffc69",
        "base_id": "anneau__tissu__t1",
        "name": "Anneau tissu",
        "slot": "anneau",
        "tier": "t1",
        "rarity_id": "common",
        "quality_id": "poor",
        "base_stats": {
          "armure": 0.0,
          "atk": 10.801452726328243,
          "blocage": 0.0,
          "bouclier": 0.0,
          "chance_double_drop_pct": 0.0,
          "cooldown_reduc": 0.0,
          "cout_reroll_pct": 0.0,
          "crit_chance": 5.684879429777397,
          "crit_degats": 150.0,
          "def_stat": 0.0,
          "degats_feu": 0.0,
          "degats_foudre": 0.0,
          "degats_glace": 0.0,
          "degats_lumiere": 0.0,
          "degats_ombre": 0.0,
          "degats_physique": 0.0,
          "degats_poison": 0.0,
          "epines": 0.0,
          "esquive": 0.0,
          "flag_boss_slayer": 0.0,
          "flag_execute": 0.0,
          "flag_reroll_free_chance": 0.0,
          "flag_resource_spirit": 0.0,
          "gain_or_pct": 0.0,
          "gain_xp_pct": 0.0,
          "gather_power_herb": 0.0,
          "gather_power_ore": 0.0,
          "gather_power_wood": 0.0,
          "hp_current": 100.0,
          "hp_max": 100.0,
          "hp_regen": 0.0,
          "precision": 0.0,
          "proc_double_coup_chance": 0.0,
          "proc_etourdissement_chance": 0.0,
          "proc_poison_chance": 0.0,
          "proc_saignement_chance": 0.0,
          "rendement_demantelement_pct": 0.0,
          "resistance_elementaire": 0.0,
          "ressources_gagnees_pct": 0.0,
          "vitesse_attaque": 1.0,
          "vitesse_craft_pct": 0.0,
          "vitesse_recolte_pct": 0.0,
          "vol_vie": 0.0
        },
        "affixes": [],
        "set_id": null,
        "gold_value": 10,
        "level_requirement": 1,
        "power_score": 133.65754374198866,
        "is_equipped": false
      },
      {
        "id": "e14b945a-b2f1-41a4-86c4-1d018d3f4539",
        "base_id": "casque__bois__t1",
        "name": "Casque en bois",
        "slot": "casque",
        "tier": "t1",
        "rarity_id": "common",
        "quality_id": "normal",
        "base_stats": {
          "armure": 0.0,
          "atk": 10.0,
          "blocage": 0.0,
          "bouclier": 0.0,
          "chance_double_drop_pct": 0.0,
          "cooldown_reduc": 0.0,
          "cout_reroll_pct": 0.0,
          "crit_chance": 5.0,
          "crit_degats": 150.0,
          "def_stat": 1.6771104898459672,
          "degats_feu": 0.0,
          "degats_foudre": 0.0,
          "degats_glace": 0.0,
          "degats_lumiere": 0.0,
          "degats_ombre": 0.0,
          "degats_physique": 0.0,
          "degats_poison": 0.0,
          "epines": 0.0,
          "esquive": 0.0,
          "flag_boss_slayer": 0.0,
          "flag_execute": 0.0,
          "flag_reroll_free_chance": 0.0,
          "flag_resource_spirit": 0.0,
          "gain_or_pct": 0.0,
          "gain_xp_pct": 0.0,
          "gather_power_herb": 0.0,
          "gather_power_ore": 0.0,
          "gather_power_wood": 0.0,
          "hp_current": 100.0,
          "hp_max": 105.49161588289635,
          "hp_regen": 0.0,
          "precision": 0.0,
          "proc_double_coup_chance": 0.0,
          "proc_etourdissement_chance": 0.0,
          "proc_poison_chance": 0.0,
          "proc_saignement_chance": 0.0,
          "rendement_demantelement_pct": 0.0,
          "resistance_elementaire": 0.0,
          "ressources_gagnees_pct": 0.0,
          "vitesse_attaque": 1.0,
          "vitesse_craft_pct": 0.0,
          "vitesse_recolte_pct": 0.0,
          "vol_vie": 0.0
        },
        "affixes": [],
        "set_id": null,
        "gold_value": 10,
        "level_requirement": 1,
        "power_score": 133.06482732305858,
        "is_equipped": false
      },
      {
        "id": "c4987f02-5d87-4f4b-b36a-0cdc7741e65d",
        "base_id": "outil_serpe__bois__t1",
        "name": "Serpe en bois",
        "slot": "outil_serpe",
        "tier": "t1",
        "rarity_id": "common",
        "quality_id": "poor",
        "base_stats": {
          "armure": 0.0,
          "atk": 10.0,
          "blocage": 0.0,
          "bouclier": 0.0,
          "chance_double_drop_pct": 0.7968773844891931,
          "cooldown_reduc": 0.0,
          "cout_reroll_pct": 0.0,
          "crit_chance": 5.0,
          "crit_degats": 150.0,
          "def_stat": 0.0,
          "degats_feu": 0.0,
          "degats_foudre": 0.0,
          "degats_glace": 0.0,
          "degats_lumiere": 0.0,
          "degats_ombre": 0.0,
          "degats_physique": 0.0,
          "degats_poison": 0.0,
          "epines": 0.0,
          "esquive": 0.0,
          "flag_boss_slayer": 0.0,
          "flag_execute": 0.0,
          "flag_reroll_free_chance": 0.0,
          "flag_resource_spirit": 0.0,
          "gain_or_pct": 0.0,
          "gain_xp_pct": 0.0,
          "gather_power_herb": 4.895270433369719,
          "gather_power_ore": 0.0,
          "gather_power_wood": 0.0,
          "hp_current": 100.0,
          "hp_max": 100.0,
          "hp_regen": 0.0,
          "precision": 0.0,
          "proc_double_coup_chance": 0.0,
          "proc_etourdissement_chance": 0.0,
          "proc_poison_chance": 0.0,
          "proc_saignement_chance": 0.0,
          "rendement_demantelement_pct": 0.0,
          "resistance_elementaire": 0.0,
          "ressources_gagnees_pct": 0.0,
          "vitesse_attaque": 1.0,
          "vitesse_craft_pct": 0.0,
          "vitesse_recolte_pct": 0.0,
          "vol_vie": 0.0
        },
        "affixes": [],
        "set_id": null,
        "gold_value": 10,
        "level_requirement": 1,
        "power_score": 130.0,
        "is_equipped": false
      },
      {
        "id": "aa2946ce-c201-4d3d-990b-e99adb0762d9",
        "base_id": "gants__cuir__t1",
        "name": "Gants en cuir",
        "slot": "gants",
        "tier": "t1",
        "rarity_id": "common",
        "quality_id": "perfect",
        "base_stats": {
          "armure": 0.0,
          "atk": 10.0,
          "blocage": 0.0,
          "bouclier": 0.0,
          "chance_double_drop_pct": 0.0,
          "cooldown_reduc": 0.0,
          "cout_reroll_pct": 0.0,
          "crit_chance": 5.0,
          "crit_degats": 150.0,
          "def_stat": 0.5074774014456652,
          "degats_feu": 0.0,
          "degats_foudre": 0.0,
          "degats_glace": 0.0,
          "degats_lumiere": 0.0,
          "degats_ombre": 0.0,
          "degats_physique": 0.0,
          "degats_poison": 0.0,
          "epines": 0.0,
          "esquive": 0.0,
          "flag_boss_slayer": 0.0,
          "flag_execute": 0.0,
          "flag_reroll_free_chance": 0.0,
          "flag_resource_spirit": 0.0,
          "gain_or_pct": 0.0,
          "gain_xp_pct": 0.0,
          "gather_power_herb": 0.0,
          "gather_power_ore": 0.0,
          "gather_power_wood": 0.0,
          "hp_current": 100.0,
          "hp_max": 100.0,
          "hp_regen": 0.0,
          "precision": 0.0,
          "proc_double_coup_chance": 0.0,
          "proc_etourdissement_chance": 0.0,
          "proc_poison_chance": 0.0,
          "proc_saignement_chance": 0.0,
          "rendement_demantelement_pct": 0.0,
          "resistance_elementaire": 0.0,
          "ressources_gagnees_pct": 0.0,
          "vitesse_attaque": 1.9723134975884715,
          "vitesse_craft_pct": 0.0,
          "vitesse_recolte_pct": 0.0,
          "vol_vie": 0.0
        },
        "affixes": [],
        "set_id": null,
        "gold_value": 10,
        "level_requirement": 1,
        "power_score": 130.7612161021685,
        "is_equipped": false
      },
      {
        "id": "c7389f8f-6420-46bd-abbf-0932a73a8b78",
        "base_id": "plastron__cuir__t1",
        "name": "Plastron en cuir",
        "slot": "plastron",
        "tier": "t1",
        "rarity_id": "common",
        "quality_id": "poor",
        "base_stats": {
          "armure": 0.0,
          "atk": 10.0,
          "blocage": 0.0,
          "bouclier": 0.0,
          "chance_double_drop_pct": 0.0,
          "cooldown_reduc": 0.0,
          "cout_reroll_pct": 0.0,
          "crit_chance": 5.0,
          "crit_degats": 150.0,
          "def_stat": 2.090551123460944,
          "degats_feu": 0.0,
          "degats_foudre": 0.0,
          "degats_glace": 0.0,
          "degats_lumiere": 0.0,
          "degats_ombre": 0.0,
          "degats_physique": 0.0,
          "degats_poison": 0.0,
          "epines": 0.0,
          "esquive": 0.0,
          "flag_boss_slayer": 0.0,
          "flag_execute": 0.0,
          "flag_reroll_free_chance": 0.0,
          "flag_resource_spirit": 0.0,
          "gain_or_pct": 0.0,
          "gain_xp_pct": 0.0,
          "gather_power_herb": 0.0,
          "gather_power_ore": 0.0,
          "gather_power_wood": 0.0,
          "hp_current": 100.0,
          "hp_max": 106.78164156857103,
          "hp_regen": 0.0,
          "precision": 0.0,
          "proc_double_coup_chance": 0.0,
          "proc_etourdissement_chance": 0.0,
          "proc_poison_chance": 0.0,
          "proc_saignement_chance": 0.0,
          "rendement_demantelement_pct": 0.0,
          "resistance_elementaire": 0.0,
          "ressources_gagnees_pct": 0.0,
          "vitesse_attaque": 1.0,
          "vitesse_craft_pct": 0.0,
          "vitesse_recolte_pct": 0.0,
          "vol_vie": 0.0
        },
        "affixes": [],
        "set_id": null,
        "gold_value": 10,
        "level_requirement": 1,
        "power_score": 133.81399084204853,
        "is_equipped": false
      },
      {
        "id": "77510c77-e1a5-4fed-86a6-13bdf164952e",
        "base_id": "bouclier__bois__t1",
        "name": "Bouclier en bois",
        "slot": "bouclier",
        "tier": "t1",
        "rarity_id": "common",
        "quality_id": "poor",
        "base_stats": {
          "armure": 0.0,
          "atk": 10.0,
          "blocage": 1.341064624446747,
          "bouclier": 0.0,
          "chance_double_drop_pct": 0.0,
          "cooldown_reduc": 0.0,
          "cout_reroll_pct": 0.0,
          "crit_chance": 5.0,
          "crit_degats": 150.0,
          "def_stat": 3.0418484969333273,
          "degats_feu": 0.0,
          "degats_foudre": 0.0,
          "degats_glace": 0.0,
          "degats_lumiere": 0.0,
          "degats_ombre": 0.0,
          "degats_physique": 0.0,
          "degats_poison": 0.0,
          "epines": 0.0,
          "esquive": 0.0,
          "flag_boss_slayer": 0.0,
          "flag_execute": 0.0,
          "flag_reroll_free_chance": 0.0,
          "flag_resource_spirit": 0.0,
          "gain_or_pct": 0.0,
          "gain_xp_pct": 0.0,
          "gather_power_herb": 0.0,
          "gather_power_ore": 0.0,
          "gather_power_wood": 0.0,
          "hp_current": 100.0,
          "hp_max": 100.0,
          "hp_regen": 0.0,
          "precision": 0.0,
          "proc_double_coup_chance": 0.0,
          "proc_etourdissement_chance": 0.0,
          "proc_poison_chance": 0.0,
          "proc_saignement_chance": 0.0,
          "rendement_demantelement_pct": 0.0,
          "resistance_elementaire": 0.0,
          "ressources_gagnees_pct": 0.0,
          "vitesse_attaque": 1.0,
          "vitesse_craft_pct": 0.0,
          "vitesse_recolte_pct": 0.0,
          "vol_vie": 0.0
        },
        "affixes": [],
        "set_id": null,
        "gold_value": 10,
        "level_requirement": 1,
        "power_score": 134.5627727454,
        "is_equipped": false
      },
      {
        "id": "2841e09c-89d0-4247-a868-15cca8124674",
        "base_id": "tool__pioche__t1",
        "name": "Pioche T1",
        "slot": "tool_ore",
        "tier": "t1",
        "rarity_id": "common",
        "quality_id": "normal",
        "base_stats": {
          "armure": 0.0,
          "atk": 10.0,
          "blocage": 0.0,
          "bouclier": 0.0,
          "chance_double_drop_pct": 0.0,
          "cooldown_reduc": 0.0,
          "cout_reroll_pct": 0.0,
          "crit_chance": 5.0,
          "crit_degats": 150.0,
          "def_stat": 0.0,
          "degats_feu": 0.0,
          "degats_foudre": 0.0,
          "degats_glace": 0.0,
          "degats_lumiere": 0.0,
          "degats_ombre": 0.0,
          "degats_physique": 0.0,
          "degats_poison": 0.0,
          "epines": 0.0,
          "esquive": 0.0,
          "flag_boss_slayer": 0.0,
          "flag_execute": 0.0,
          "flag_reroll_free_chance": 0.0,
          "flag_resource_spirit": 0.0,
          "gain_or_pct": 0.0,
          "gain_xp_pct": 0.0,
          "gather_power_herb": 0.0,
          "gather_power_ore": 6.17865511817624,
          "gather_power_wood": 0.0,
          "hp_current": 100.0,
          "hp_max": 100.0,
          "hp_regen": 0.0,
          "precision": 0.0,
          "proc_double_coup_chance": 0.0,
          "proc_etourdissement_chance": 0.0,
          "proc_poison_chance": 0.0,
          "proc_saignement_chance": 0.0,
          "rendement_demantelement_pct": 0.0,
          "resistance_elementaire": 0.0,
          "ressources_gagnees_pct": 0.0,
          "vitesse_attaque": 1.0,
          "vitesse_craft_pct": 0.0,
          "vitesse_recolte_pct": 0.0,
          "vol_vie": 0.0
        },
        "affixes": [],
        "set_id": null,
        "gold_value": 10,
        "level_requirement": 1,
        "power_score": 130.0,
        "is_equipped": false
      }
    ],
    "potions": {},
    "resources": {
      "bois_tendre": 150,
      "pierre_brute": 121,
      "fibres_sauvages": 30,
      "eau_claire": 7,
      "cristal_feu": 2,
      "fragment_combat": 1,
      "essence_forge": 2
    },
    "gold": 916,
    "buffs": [],
    "current_zone_id": "prairie_des_jeunes_pousses",
    "unlocked_stations": [
      "atelier"
    ],
    "combat_stats": {
      "kills": 212,
      "deaths": 0,
      "damage_dealt": 75457,
      "damage_taken": 21,
      "crits": 0,
      "boss_kills": 3
    }
  },
  "skills": {
    "unlocked_skills": []
  },
  "station_upgrades": {
    "station_levels": {}
  }
}